setup.py
pancakeswap/__init__.py
pancakeswap/common_func.py
pancakeswap/pancakeswap.py
pancakeswap/pancakeswap_abi.py
python_pancakeswap.egg-info/PKG-INFO
python_pancakeswap.egg-info/SOURCES.txt
python_pancakeswap.egg-info/dependency_links.txt
python_pancakeswap.egg-info/requires.txt
python_pancakeswap.egg-info/top_level.txt
python_pancakeswap.egg-info/zip-safe